README.txt
beacon.py
beacon_example_cli.py
beacon_example_srv.py
setup.py
netbeacon.egg-info/PKG-INFO
netbeacon.egg-info/SOURCES.txt
netbeacon.egg-info/dependency_links.txt
netbeacon.egg-info/requires.txt
netbeacon.egg-info/top_level.txt