Metadata-Version: 1.0
Name: netbeacon
Version: 1.0
Summary: UNKNOWN
Home-page: http://www.smallbulb.net
Author: David Siroky
Author-email: siroky@dasir.cz
License: MIT License
Keywords: network,host,beacon,discovery,UDP,broadcast
Platform: UNKNOWN
Classifier: Operating System :: OS Independent
Classifier: Development Status :: 5 - Production/Stable
Classifier: Intended Audience :: Developers
Classifier: License :: OSI Approved :: MIT License
Classifier: Topic :: System :: Networking
Classifier: Topic :: System :: Distributed Computing
Classifier: Topic :: Communications
Classifier: Topic :: Software Development :: Libraries
